rhodium/__init__.py
rhodium/brush.py
rhodium/cache.py
rhodium/classification.py
rhodium/config.py
rhodium/decorators.py
rhodium/excel.py
rhodium/expr.py
rhodium/ffi.py
rhodium/model.py
rhodium/openmdao.py
rhodium/optimization.py
rhodium/plot.py
rhodium/rbridge.py
rhodium/robustness.py
rhodium/sa.py
rhodium/sampling.py
rhodium/utils.py
rhodium/test/__init__.py
rhodium/test/brush_test.py
rhodium/test/cache_test.py
rhodium/test/excel_test.py
rhodium/test/ffi_test.py
rhodium/test/model_test.py
rhodium/test/openmdao_test.py
rhodium/test/optimization_test.py
rhodium/test/sampling_test.py
Rhodium-1.4.0.dist-info/COPYING
Rhodium-1.4.0.dist-info/METADATA
Rhodium-1.4.0.dist-info/WHEEL
Rhodium-1.4.0.dist-info/top_level.txt
Rhodium-1.4.0.dist-info/RECORD
