Metadata-Version: 2.1
Name: Rhodium
Version: 1.4.0
Summary: Robust decision making and exploratory modelling in Python
Author-email: David Hadka <dhadka@users.noreply.github.com>
License: GNU GENERAL PUBLIC LICENSE
Project-URL: Homepage, https://github.com/Project-Platypus/Rhodium
Project-URL: Bug Tracker, https://github.com/Project-Platypus/Rhodium/issues
Requires-Python: >=3.8
License-File: COPYING
Requires-Dist: numpy <=1.26.4
Requires-Dist: seaborn <=0.13.2
Requires-Dist: scikit-learn <=1.5.0
Requires-Dist: mplcursors <=0.5.3
Requires-Dist: pydot <=2.0.0
Requires-Dist: SALib <=1.4.6.1
Requires-Dist: pandas
Requires-Dist: platypus-opt
Requires-Dist: prim
Provides-Extra: examples
Requires-Dist: pandas[excel] ; extra == 'examples'
Requires-Dist: pyper <=1.1.2 ; extra == 'examples'
Provides-Extra: openmdao
Requires-Dist: openmdao ; extra == 'openmdao'
Provides-Extra: test
Requires-Dist: pytest ; extra == 'test'
Requires-Dist: mock ; extra == 'test'
Requires-Dist: rhodium[examples] ; extra == 'test'
